ai_llm_router-0.1.0.dist-info/licenses/LICENSE
llm_router/__init__.py
llm_router/cli.py
llm_router/config.py
llm_router/exceptions.py
llm_router/router.py
llm_router/types.py
llm_router/providers/__init__.py
llm_router/providers/anthropic.py
llm_router/providers/base.py
llm_router/providers/openai.py
llm_router/providers/registry.py
llm_router/strategies/__init__.py
llm_router/strategies/base.py
llm_router/strategies/cost_optimized.py
llm_router/strategies/priority.py
llm_router/strategies/round_robin.py
llm_router/utils/__init__.py
llm_router/utils/cache.py
llm_router/utils/cost_tracker.py
llm_router/utils/metrics.py
llm_router/utils/monitor.py
llm_router/utils/retry.py
ai_llm_router-0.1.0.dist-info/METADATA
ai_llm_router-0.1.0.dist-info/WHEEL
ai_llm_router-0.1.0.dist-info/entry_points.txt
ai_llm_router-0.1.0.dist-info/top_level.txt
ai_llm_router-0.1.0.dist-info/RECORD
